pygmas/__init__.py
pygmas/genetic_algorithm.py
pygmas/prework.py
pygmas/pyexpr.py
pygmas/pygmas.py
pygmas/utils.py
pyGMAS-0.0.1.dist-info/LICENSE
pyGMAS-0.0.1.dist-info/METADATA
pyGMAS-0.0.1.dist-info/WHEEL
pyGMAS-0.0.1.dist-info/top_level.txt
pyGMAS-0.0.1.dist-info/RECORD
